{"pages_archives.md":"5d15bad3","posts_oauth-and-oidc.md":"e451f419","working_get-node-memory-snapshot.md":"02dd28e6","posts_setup-nginx-https-server.md":"8f911a60","posts_websocket-subprotocol.md":"27576996","posts_using-jdk-http-client-2.md":"1892df56","posts_basic-linux-server-setup.md":"2acf8b11","working_use-cobra-for-building-cli.md":"53b5dd26","index.md":"1b3e24df","pages_tags.md":"b0d31442","posts_hello-world.md":"d1d853a9","working_rust-http-service-with-hyper.md":"3197a2ed","pages_about.md":"bdb9f4e3","posts_rust-build-http-server.md":"4bfb13db","posts_using-jdk-http-client-1.md":"3e9c5758","posts_ask-gpt-react.md":"1fbc331b"}
